{
  "id": "2ad29f05-2b4f-478c-810c-d92f2514e34c",
  "matchState": "Finished",
  "timeStamp": 1759665600,
  "ticketshopUrl": "https://www.ttbl.de/tickets",
  "livestreamUrl": "https://www.dyn.sport/sport_tabletennis",
  "spectators": 680,
  "followupReport": "",
  "preliminaryReportUrl": "",
  "updateCount": null,
  "gameday": {
    "name": "5. Spieltag (2025/2026)"
  },
  "venue": {
    "name": "ARAG Centercourt",
    "adress": "Borussia-D\u00fcsseldorf-Stra\u00dfe 1",
    "zipCode": "40629",
    "place": "D\u00fcsseldorf",
    "imageUrl": "/uploads/venue/imageUrl/05307eb4-9b53-4e4a-991c-f21e2480961c.png"
  },
  "homeGames": 3,
  "awayGames": 1,
  "homeSets": 11,
  "awaySets": 5,
  "homeBalls": 171,
  "awayBalls": 131,
  "homeTeam": {
    "id": "37f65d5e-a709-4325-b62d-d04276bc15d6",
    "seasonTeamId": "b9326bfc-7e01-43f3-bc9e-1401133e03d5",
    "logoPngUrl": "/uploads/team/logoPngUrl/a5dfd114-33cb-406a-8db3-c34815a6e486.png",
    "name": "Borussia D\u00fcsseldorf",
    "rank": 3,
    "plusPoints": 16,
    "gameWins": 27,
    "setWins": 97
  },
  "awayTeam": {
    "id": "40f50bee-a69b-4f33-8063-647abf649876",
    "seasonTeamId": "b2fdb776-25c0-4782-8eb4-613cb6d3b415",
    "logoPngUrl": "/uploads/team/logoPngUrl/4ae224dc-dd52-48c3-8143-cdb40c8ded5a.png",
    "name": "TTF Liebherr Ochsenhausen",
    "rank": 4,
    "plusPoints": 14,
    "gameWins": 24,
    "setWins": 83
  },
  "homePlayerOne": {
    "id": "e18bf6f7-d2c9-4200-b303-22934acd43a8",
    "imageUrl": "/uploads/player/imageUrl/84d061fb-0697-4a08-a8ac-d20af8258b91.png",
    "firstName": "Kanak",
    "lastName": "Jha"
  },
  "homePlayerTwo": {
    "id": "c57bc4b0-983d-4563-99d8-fbe676541658",
    "imageUrl": "/uploads/player/imageUrl/e0211d92-061c-4394-969a-4a9a42334af2.png",
    "firstName": "Yongyin",
    "lastName": "Li"
  },
  "homePlayerThree": {
    "id": "5f31f286-16c1-407e-a7a6-52f6d6ecfe40",
    "imageUrl": "/uploads/player/imageUrl/fa566a36-4330-4140-8c9d-7285aeb363a8.png",
    "firstName": "Anton",
    "lastName": "K\u00e4llberg"
  },
  "homeSubstitutePlayerOne": null,
  "homeSubstitutePlayerTwo": null,
  "homeSubstitutePlayerThree": null,
  "guestPlayerOne": {
    "id": "84d5e75e-0f96-47a2-a659-b02185d8d0ec",
    "imageUrl": "/uploads/player/imageUrl/1139b91f-f312-4cc9-b93c-794d7c00d58c.png",
    "firstName": "Tiago",
    "lastName": "Abiodun"
  },
  "guestPlayerTwo": {
    "id": "e8305243-fb98-44f2-a97c-8119e0d68768",
    "imageUrl": "/uploads/player/imageUrl/821b007a-9dbd-400e-aa53-370fbf08bb24.png",
    "firstName": "Andreas",
    "lastName": "Levenko"
  },
  "guestPlayerThree": {
    "id": "e491f9e9-5d86-4088-812f-5293a1253f5a",
    "imageUrl": "/uploads/player/imageUrl/14a15b7a-d67e-433e-8a92-ce5790c45b15.png",
    "firstName": "Leonardo",
    "lastName": "Iizuka"
  },
  "guestSubstitutePlayerOne": null,
  "guestSubstitutePlayerTwo": null,
  "guestSubstitutePlayerThree": null,
  "games": [
    {
      "id": "12ac6b35-0003-49c9-bc12-9224283df63c",
      "index": 1,
      "gameState": "Finished",
      "winnerSide": null,
      "homeTimeoutUsed": 0,
      "awayTimeoutUsed": 0,
      "homeSets": 2,
      "awaySets": 3,
      "set1HomeScore": 11,
      "set1AwayScore": 6,
      "set2HomeScore": 9,
      "set2AwayScore": 11,
      "set3HomeScore": 11,
      "set3AwayScore": 6,
      "set4HomeScore": 15,
      "set4AwayScore": 17,
      "set5HomeScore": 8,
      "set5AwayScore": 11,
      "scoringUpdates": [],
      "homePlayer": {
        "id": "e18bf6f7-d2c9-4200-b303-22934acd43a8",
        "imageUrl": "/uploads/player/imageUrl/84d061fb-0697-4a08-a8ac-d20af8258b91.png",
        "firstName": "Kanak",
        "lastName": "Jha"
      },
      "awayPlayer": {
        "id": "e8305243-fb98-44f2-a97c-8119e0d68768",
        "imageUrl": "/uploads/player/imageUrl/821b007a-9dbd-400e-aa53-370fbf08bb24.png",
        "firstName": "Andreas",
        "lastName": "Levenko"
      },
      "homeDouble": null,
      "awayDouble": null,
      "cards": [],
      "homePointsOnServe": 0,
      "awayPointsOnServe": 0,
      "homePointsOnReturn": 0,
      "awayPointsOnReturn": 0,
      "homePointsInARow": 0,
      "awayPointsInARow": 0,
      "homeLuckyPoints": 0,
      "awayLuckyPoints": 0,
      "homeHighestLead": 0,
      "awayHighestLead": 0,
      "homeMatchPoints": 0,
      "awayMatchPoints": 0
    },
    {
      "id": "30cb28d4-0afa-4930-9e65-ecf5c6353834",
      "index": 2,
      "gameState": "Finished",
      "winnerSide": null,
      "homeTimeoutUsed": 0,
      "awayTimeoutUsed": 0,
      "homeSets": 3,
      "awaySets": 1,
      "set1HomeScore": 9,
      "set1AwayScore": 11,
      "set2HomeScore": 11,
      "set2AwayScore": 5,
      "set3HomeScore": 11,
      "set3AwayScore": 6,
      "set4HomeScore": 11,
      "set4AwayScore": 5,
      "set5HomeScore": null,
      "set5AwayScore": null,
      "scoringUpdates": [],
      "homePlayer": {
        "id": "c57bc4b0-983d-4563-99d8-fbe676541658",
        "imageUrl": "/uploads/player/imageUrl/e0211d92-061c-4394-969a-4a9a42334af2.png",
        "firstName": "Yongyin",
        "lastName": "Li"
      },
      "awayPlayer": {
        "id": "84d5e75e-0f96-47a2-a659-b02185d8d0ec",
        "imageUrl": "/uploads/player/imageUrl/1139b91f-f312-4cc9-b93c-794d7c00d58c.png",
        "firstName": "Tiago",
        "lastName": "Abiodun"
      },
      "homeDouble": null,
      "awayDouble": null,
      "cards": [],
      "homePointsOnServe": 0,
      "awayPointsOnServe": 0,
      "homePointsOnReturn": 0,
      "awayPointsOnReturn": 0,
      "homePointsInARow": 0,
      "awayPointsInARow": 0,
      "homeLuckyPoints": 0,
      "awayLuckyPoints": 0,
      "homeHighestLead": 0,
      "awayHighestLead": 0,
      "homeMatchPoints": 0,
      "awayMatchPoints": 0
    },
    {
      "id": "1a0805de-4c67-4c37-90dd-3dbb22c2a530",
      "index": 3,
      "gameState": "Finished",
      "winnerSide": null,
      "homeTimeoutUsed": 0,
      "awayTimeoutUsed": 0,
      "homeSets": 3,
      "awaySets": 0,
      "set1HomeScore": 11,
      "set1AwayScore": 5,
      "set2HomeScore": 11,
      "set2AwayScore": 9,
      "set3HomeScore": 11,
      "set3AwayScore": 7,
      "set4HomeScore": null,
      "set4AwayScore": null,
      "set5HomeScore": null,
      "set5AwayScore": null,
      "scoringUpdates": [],
      "homePlayer": {
        "id": "5f31f286-16c1-407e-a7a6-52f6d6ecfe40",
        "imageUrl": "/uploads/player/imageUrl/fa566a36-4330-4140-8c9d-7285aeb363a8.png",
        "firstName": "Anton",
        "lastName": "K\u00e4llberg"
      },
      "awayPlayer": {
        "id": "e491f9e9-5d86-4088-812f-5293a1253f5a",
        "imageUrl": "/uploads/player/imageUrl/14a15b7a-d67e-433e-8a92-ce5790c45b15.png",
        "firstName": "Leonardo",
        "lastName": "Iizuka"
      },
      "homeDouble": null,
      "awayDouble": null,
      "cards": [],
      "homePointsOnServe": 0,
      "awayPointsOnServe": 0,
      "homePointsOnReturn": 0,
      "awayPointsOnReturn": 0,
      "homePointsInARow": 0,
      "awayPointsInARow": 0,
      "homeLuckyPoints": 0,
      "awayLuckyPoints": 0,
      "homeHighestLead": 0,
      "awayHighestLead": 0,
      "homeMatchPoints": 0,
      "awayMatchPoints": 0
    },
    {
      "id": "c6614de7-2589-4777-b892-3e74d313e8d6",
      "index": 4,
      "gameState": "Finished",
      "winnerSide": null,
      "homeTimeoutUsed": 0,
      "awayTimeoutUsed": 0,
      "homeSets": 3,
      "awaySets": 1,
      "set1HomeScore": 9,
      "set1AwayScore": 11,
      "set2HomeScore": 11,
      "set2AwayScore": 8,
      "set3HomeScore": 11,
      "set3AwayScore": 8,
      "set4HomeScore": 11,
      "set4AwayScore": 5,
      "set5HomeScore": null,
      "set5AwayScore": null,
      "scoringUpdates": [],
      "homePlayer": {
        "id": "e18bf6f7-d2c9-4200-b303-22934acd43a8",
        "imageUrl": "/uploads/player/imageUrl/84d061fb-0697-4a08-a8ac-d20af8258b91.png",
        "firstName": "Kanak",
        "lastName": "Jha"
      },
      "awayPlayer": {
        "id": "84d5e75e-0f96-47a2-a659-b02185d8d0ec",
        "imageUrl": "/uploads/player/imageUrl/1139b91f-f312-4cc9-b93c-794d7c00d58c.png",
        "firstName": "Tiago",
        "lastName": "Abiodun"
      },
      "homeDouble": null,
      "awayDouble": null,
      "cards": [],
      "homePointsOnServe": 0,
      "awayPointsOnServe": 0,
      "homePointsOnReturn": 0,
      "awayPointsOnReturn": 0,
      "homePointsInARow": 0,
      "awayPointsInARow": 0,
      "homeLuckyPoints": 0,
      "awayLuckyPoints": 0,
      "homeHighestLead": 0,
      "awayHighestLead": 0,
      "homeMatchPoints": 0,
      "awayMatchPoints": 0
    },
    {
      "id": "6dcbf7ca-d276-4a4b-b660-d00232931688",
      "index": 5,
      "gameState": "Inactive",
      "winnerSide": null,
      "homeTimeoutUsed": 0,
      "awayTimeoutUsed": 0,
      "homeSets": 0,
      "awaySets": 0,
      "set1HomeScore": null,
      "set1AwayScore": null,
      "set2HomeScore": null,
      "set2AwayScore": null,
      "set3HomeScore": null,
      "set3AwayScore": null,
      "set4HomeScore": null,
      "set4AwayScore": null,
      "set5HomeScore": null,
      "set5AwayScore": null,
      "scoringUpdates": [],
      "homePlayer": null,
      "awayPlayer": null,
      "homeDouble": {
        "id": "5f31f286-16c1-407e-a7a6-52f6d6ecfe40|c57bc4b0-983d-4563-99d8-fbe676541658",
        "leaguePlayerOne": {
          "id": "5f31f286-16c1-407e-a7a6-52f6d6ecfe40",
          "imageUrl": "/uploads/player/imageUrl/fa566a36-4330-4140-8c9d-7285aeb363a8.png",
          "firstName": "Anton",
          "lastName": "K\u00e4llberg"
        },
        "leaguePlayerTwo": {
          "id": "c57bc4b0-983d-4563-99d8-fbe676541658",
          "imageUrl": "/uploads/player/imageUrl/e0211d92-061c-4394-969a-4a9a42334af2.png",
          "firstName": "Yongyin",
          "lastName": "Li"
        }
      },
      "awayDouble": {
        "id": "e491f9e9-5d86-4088-812f-5293a1253f5a|e8305243-fb98-44f2-a97c-8119e0d68768",
        "leaguePlayerOne": {
          "id": "e491f9e9-5d86-4088-812f-5293a1253f5a",
          "imageUrl": "/uploads/player/imageUrl/14a15b7a-d67e-433e-8a92-ce5790c45b15.png",
          "firstName": "Leonardo",
          "lastName": "Iizuka"
        },
        "leaguePlayerTwo": {
          "id": "e8305243-fb98-44f2-a97c-8119e0d68768",
          "imageUrl": "/uploads/player/imageUrl/821b007a-9dbd-400e-aa53-370fbf08bb24.png",
          "firstName": "Andreas",
          "lastName": "Levenko"
        }
      },
      "cards": [],
      "homePointsOnServe": 0,
      "awayPointsOnServe": 0,
      "homePointsOnReturn": 0,
      "awayPointsOnReturn": 0,
      "homePointsInARow": 0,
      "awayPointsInARow": 0,
      "homeLuckyPoints": 0,
      "awayLuckyPoints": 0,
      "homeHighestLead": 0,
      "awayHighestLead": 0,
      "homeMatchPoints": 0,
      "awayMatchPoints": 0
    }
  ],
  "homeDouble": {
    "id": "5f31f286-16c1-407e-a7a6-52f6d6ecfe40|c57bc4b0-983d-4563-99d8-fbe676541658",
    "leaguePlayerOne": {
      "id": "5f31f286-16c1-407e-a7a6-52f6d6ecfe40",
      "imageUrl": "/uploads/player/imageUrl/fa566a36-4330-4140-8c9d-7285aeb363a8.png",
      "firstName": "Anton",
      "lastName": "K\u00e4llberg"
    },
    "leaguePlayerTwo": {
      "id": "c57bc4b0-983d-4563-99d8-fbe676541658",
      "imageUrl": "/uploads/player/imageUrl/e0211d92-061c-4394-969a-4a9a42334af2.png",
      "firstName": "Yongyin",
      "lastName": "Li"
    }
  },
  "awayDouble": {
    "id": "e491f9e9-5d86-4088-812f-5293a1253f5a|e8305243-fb98-44f2-a97c-8119e0d68768",
    "leaguePlayerOne": {
      "id": "e491f9e9-5d86-4088-812f-5293a1253f5a",
      "imageUrl": "/uploads/player/imageUrl/14a15b7a-d67e-433e-8a92-ce5790c45b15.png",
      "firstName": "Leonardo",
      "lastName": "Iizuka"
    },
    "leaguePlayerTwo": {
      "id": "e8305243-fb98-44f2-a97c-8119e0d68768",
      "imageUrl": "/uploads/player/imageUrl/821b007a-9dbd-400e-aa53-370fbf08bb24.png",
      "firstName": "Andreas",
      "lastName": "Levenko"
    }
  }
}